ficaptcha/__init__.py
ficaptcha/audio.py
ficaptcha/generate.py
ficaptcha/image.py
ficaptcha/process.py
ficaptcha-1.0.4.dist-info/LICENSE
ficaptcha-1.0.4.dist-info/METADATA
ficaptcha-1.0.4.dist-info/WHEEL
ficaptcha-1.0.4.dist-info/top_level.txt
ficaptcha-1.0.4.dist-info/RECORD
