Metadata-Version: 2.1
Name: ficaptcha
Version: 1.0.4
Summary: Simple captcha
Home-page: https://github.com/0x7o/fiCaptcha
Author: Danil Kononyuk
Author-email: me@0x7o.link
License: UNKNOWN
Platform: UNKNOWN
Requires-Python: >=3.6
License-File: LICENSE
